LICENSE.txt
README.md
setup.cfg
setup.py
Topsis_aryan_101903453.egg-info/PKG-INFO
Topsis_aryan_101903453.egg-info/SOURCES.txt
Topsis_aryan_101903453.egg-info/dependency_links.txt
Topsis_aryan_101903453.egg-info/top_level.txt
aryan/__init__.py
aryan/topsis.py