Metadata-Version: 2.1
Name: Topsis-aryan-101903453
Version: 0.0.5
Summary: Topsis
Home-page: UNKNOWN
Author: aryan
Author-email: <asandhu_be19@thapar.edu>
License: UNKNOWN
Keywords: python,Topsis
Platform: UNKNOWN
Classifier: Development Status :: 1 - Planning
Classifier: Intended Audience :: Developers
Classifier: Programming Language :: Python :: 3
Classifier: Operating System :: Unix
Classifier: Operating System :: MacOS :: MacOS X
Classifier: Operating System :: Microsoft :: Windows
